pdfcor/__init__.py
pdfcor/cli.py
pdfcor/core.py
pdfcor/utils.py
pdfcor-0.2.0.dist-info/LICENSE
pdfcor-0.2.0.dist-info/METADATA
pdfcor-0.2.0.dist-info/WHEEL
pdfcor-0.2.0.dist-info/entry_points.txt
pdfcor-0.2.0.dist-info/RECORD
