Metadata-Version: 2.1
Name: pdfcor
Version: 0.2.0
Summary: 
Author: infocornouaille
Author-email: 90894019+infocornouaille@users.noreply.github.com
Requires-Python: >=3.9,<4.0
Classifier: Programming Language :: Python :: 3
Classifier: Programming Language :: Python :: 3.9
Classifier: Programming Language :: Python :: 3.10
Classifier: Programming Language :: Python :: 3.11
Classifier: Programming Language :: Python :: 3.12
Requires-Dist: pillow (>=10.4.0,<11.0.0)
Requires-Dist: pymupdf (>=1.24.11,<2.0.0)
